LICENSE
MANIFEST.in
README.rst
setup.cfg
setup.py
drf_hmac_auth.egg-info/PKG-INFO
drf_hmac_auth.egg-info/SOURCES.txt
drf_hmac_auth.egg-info/dependency_links.txt
drf_hmac_auth.egg-info/top_level.txt
hmac_auth/HMACToken.py
hmac_auth/__init__.py
hmac_auth/models.py
hmac_auth/permissions.py
hmac_auth/serializers.py